Rails102/README.md
Rails102/__init__.py
Rails102/__main__.py
Rails102/file.epub
Rails102/index.html
Rails102/css/__init__.py
Rails102/css/annotations.css
Rails102/css/main.css
Rails102/css/normalize.css
Rails102/css/popup.css
Rails102/font/__init__.py
Rails102/font/fontello.eot
Rails102/font/fontello.svg
Rails102/font/fontello.ttf
Rails102/font/fontello.woff
Rails102/img/__init__.py
Rails102/img/annotator-glyph-sprite.png
Rails102/img/annotator-icon-sprite.png
Rails102/img/apple-touch-icon.png
Rails102/img/cancelfullscreen.png
Rails102/img/close.png
Rails102/img/fullscreen.png
Rails102/img/loader.gif
Rails102/img/menu-icon.png
Rails102/img/save.png
Rails102/img/saved.png
Rails102/img/settings-s.png
Rails102/img/settings.png
Rails102/img/star.png
Rails102/js/__init__.py
Rails102/js/epub.js
Rails102/js/epub.min.js
Rails102/js/epub.min.map
Rails102/js/hooks.min.js
Rails102/js/hooks.min.map
Rails102/js/reader.js
Rails102/js/reader.js.map
Rails102/js/reader.min.js
Rails102/js/reader.min.map
Rails102/js/hooks/__init__.py
Rails102/js/hooks/extensions/__init__.py
Rails102/js/hooks/extensions/highlight.js
Rails102/js/libs/__init__.py
Rails102/js/libs/jquery.min.js
Rails102/js/libs/localforage.min.js
Rails102/js/libs/screenfull.js
Rails102/js/libs/screenfull.min.js
Rails102/js/libs/zip.min.js
Rails102/js/plugins/__init__.py
Rails102/js/plugins/hypothesis.js
Rails102/js/plugins/search.js
rails_102-2024.3.1.0.dist-info/METADATA
rails_102-2024.3.1.0.dist-info/WHEEL
rails_102-2024.3.1.0.dist-info/entry_points.txt
rails_102-2024.3.1.0.dist-info/top_level.txt
rails_102-2024.3.1.0.dist-info/RECORD
